keyedstablehash/__init__.py
keyedstablehash/canonical.py
keyedstablehash/py.typed
keyedstablehash/siphash.py
keyedstablehash/stable.py
keyedstablehash/vectorized.py
keyedstablehash-0.0.5.dist-info/licenses/LICENSE.txt
keyedstablehash-0.0.5.dist-info/METADATA
keyedstablehash-0.0.5.dist-info/WHEEL
keyedstablehash-0.0.5.dist-info/top_level.txt
keyedstablehash-0.0.5.dist-info/RECORD
