Metadata-Version: 2.4
Name: keyedstablehash
Version: 0.0.5
Summary: Stable, keyed hashing for Python objects and columnar data. Think `stablehash`, but with SipHash-like keyed PRF semantics so hashes are deterministic for a given key and resistant to adversarial inputs.
Home-page: https://github.com/shloktech/keyedstablehash
Author: Shlok Tadilkar
Author-email: shloktadilkar@gmail.com
Project-URL: Source, https://github.com/shloktech/keyedstablehash
Project-URL: Tracker, https://github.com/shloktech/keyedstablehash/issues
Project-URL: Documentation, https://github.com/shloktech/keyedstablehash#readme
Classifier: Programming Language :: Python :: 3
Classifier: License :: OSI Approved :: MIT License
Classifier: Operating System :: OS Independent
Requires-Python: >=3.7
License-File: LICENSE.txt
Requires-Dist: numpy>=1.24
Provides-Extra: dataframes
Requires-Dist: pandas; extra == "dataframes"
Provides-Extra: arrow
Requires-Dist: pyarrow; extra == "arrow"
Provides-Extra: polars
Requires-Dist: polars; extra == "polars"
Dynamic: author
Dynamic: author-email
Dynamic: classifier
Dynamic: description
Dynamic: description-content-type
Dynamic: home-page
Dynamic: license-file
Dynamic: project-url
Dynamic: provides-extra
Dynamic: requires-dist
Dynamic: requires-python
Dynamic: summary
